acnportal/__init__.py
acnportal/acndata/__init__.py
acnportal/acndata/data_client.py
acnportal/acndata/utils.py
acnportal/acnsim/__init__.py
acnportal/acnsim/base.py
acnportal/acnsim/interface.py
acnportal/acnsim/simulator.py
acnportal/acnsim/analysis/__init__.py
acnportal/acnsim/analysis/tests/__init__.py
acnportal/acnsim/analysis/tests/test_analysis.py
acnportal/acnsim/events/__init__.py
acnportal/acnsim/events/acndata_events.py
acnportal/acnsim/events/event.py
acnportal/acnsim/events/event_queue.py
acnportal/acnsim/events/stochastic_events.py
acnportal/acnsim/events/tests/__init__.py
acnportal/acnsim/events/tests/test_event_queue.py
acnportal/acnsim/events/tests/test_stochastic_events.py
acnportal/acnsim/models/__init__.py
acnportal/acnsim/models/battery.py
acnportal/acnsim/models/ev.py
acnportal/acnsim/models/evse.py
acnportal/acnsim/models/tests/__init__.py
acnportal/acnsim/models/tests/test_EV.py
acnportal/acnsim/models/tests/test_EVSE.py
acnportal/acnsim/models/tests/test_battery.py
acnportal/acnsim/network/__init__.py
acnportal/acnsim/network/charging_network.py
acnportal/acnsim/network/current.py
acnportal/acnsim/network/sites/__init__.py
acnportal/acnsim/network/sites/auto_acn.py
acnportal/acnsim/network/sites/caltech_acn.py
acnportal/acnsim/network/sites/jpl_acn.py
acnportal/acnsim/network/sites/office001_acn.py
acnportal/acnsim/network/tests/__init__.py
acnportal/acnsim/network/tests/test_current.py
acnportal/acnsim/network/tests/test_network.py
acnportal/acnsim/tests/__init__.py
acnportal/acnsim/tests/test_base.py
acnportal/acnsim/tests/test_interface.py
acnportal/acnsim/tests/test_simulator.py
acnportal/algorithms/__init__.py
acnportal/algorithms/base_algorithm.py
acnportal/algorithms/postprocessing.py
acnportal/algorithms/preprocessing.py
acnportal/algorithms/sorted_algorithms.py
acnportal/algorithms/uncontrolled_charging.py
acnportal/algorithms/upper_bound_estimator.py
acnportal/algorithms/utils.py
acnportal/algorithms/tests/__init__.py
acnportal-0.3.3.dist-info/LICENSE.txt
acnportal-0.3.3.dist-info/METADATA
acnportal-0.3.3.dist-info/WHEEL
acnportal-0.3.3.dist-info/top_level.txt
acnportal-0.3.3.dist-info/RECORD
