Metadata-Version: 2.1
Name: acnportal
Version: 0.3.3
Summary: A package of tools for large-scale EV charging research.
Home-page: https://github.com/zach401/acnportal
Author: Zachary Lee, Sunash Sharma
Author-email: ev-help@caltech.edu
Classifier: Development Status :: 3 - Alpha
Classifier: Programming Language :: Python
Classifier: License :: OSI Approved :: BSD License
Classifier: Operating System :: OS Independent
License-File: LICENSE.txt
Requires-Dist: numpy
Requires-Dist: pandas
Requires-Dist: matplotlib
Requires-Dist: requests
Requires-Dist: pytz
Requires-Dist: typing_extensions
Requires-Dist: scikit-learn
Provides-Extra: all
Requires-Dist: scikit-learn; extra == "all"
Provides-Extra: scikit-learn
Requires-Dist: scikit-learn; extra == "scikit-learn"
